aiohttp_msal/__init__.py
aiohttp_msal/helpers.py
aiohttp_msal/msal_async.py
aiohttp_msal/redis_tools.py
aiohttp_msal/routes.py
aiohttp_msal/settings.py
aiohttp_msal/settings_base.py
aiohttp_msal/utils.py
aiohttp_msal-1.0.9.dist-info/WHEEL
aiohttp_msal-1.0.9.dist-info/METADATA
aiohttp_msal-1.0.9.dist-info/RECORD
