Metadata-Version: 2.3
Name: aiohttp-msal
Version: 1.0.9
Summary: Helper Library to use the Microsoft Authentication Library (MSAL) with aiohttp
Keywords: aiohttp,asyncio,msal,oauth
Author: Johann Kellerman
Author-email: Johann Kellerman <kellerza@gmail.com>
License: The MIT License (MIT)
Classifier: Development Status :: 4 - Beta
Classifier: Intended Audience :: Developers
Classifier: Natural Language :: English
Classifier: Programming Language :: Python :: 3 :: Only
Classifier: Programming Language :: Python :: 3.12
Classifier: Programming Language :: Python :: 3.13
Classifier: Programming Language :: Python :: 3.14
Requires-Dist: aiohttp>=3.11.18,<3.13
Requires-Dist: aiohttp-session[aioredis]>=2.12.1,<3
Requires-Dist: attrs>=25.3,<26
Requires-Dist: msal>=1.32.3,<2
Requires-Dist: aiohttp-session[aioredis]>=2.12.1,<3 ; extra == 'aioredis'
Requires-Python: >=3.12
Project-URL: Homepage, https://github.com/kellerza/aiohttp_msal
Provides-Extra: aioredis
